odoo/addons/purchase_reception_notify/README.rst
odoo/addons/purchase_reception_notify/__init__.py
odoo/addons/purchase_reception_notify/__manifest__.py
odoo/addons/purchase_reception_notify/hooks.py
odoo/addons/purchase_reception_notify/data/mail.xml
odoo/addons/purchase_reception_notify/i18n/purchase_reception_notify.pot
odoo/addons/purchase_reception_notify/models/__init__.py
odoo/addons/purchase_reception_notify/models/stock_picking.py
odoo/addons/purchase_reception_notify/readme/CONTRIBUTORS.rst
odoo/addons/purchase_reception_notify/readme/DESCRIPTION.rst
odoo/addons/purchase_reception_notify/readme/USAGE.rst
odoo/addons/purchase_reception_notify/static/description/icon.png
odoo/addons/purchase_reception_notify/static/description/index.html
odoo/addons/purchase_reception_notify/tests/__init__.py
odoo/addons/purchase_reception_notify/tests/test_purchase_reception_notify.py
odoo11_addon_purchase_reception_notify-11.0.1.0.0.99.dev6.dist-info/METADATA
odoo11_addon_purchase_reception_notify-11.0.1.0.0.99.dev6.dist-info/WHEEL
odoo11_addon_purchase_reception_notify-11.0.1.0.0.99.dev6.dist-info/top_level.txt
odoo11_addon_purchase_reception_notify-11.0.1.0.0.99.dev6.dist-info/RECORD
